<?xml version="1.0" encoding="UTF-8"?>
<beans xmlns="http://www.springframework.org/schema/beans"
	xmlns:xsi="http://www.w3.org/2001/XMLSchema-instance"
	xsi:schemaLocation="http://www.springframework.org/schema/beans http://www.springframework.org/schema/beans/spring-beans-2.5.xsd">
	
	<bean id="sm2DataBiz" class="com.nbcedu.function.schoolmaster2.biz.impl.SM2DataBizImpl">
		<property name="sm2DataDao" ref="sm2DataDao"></property>
	</bean>
	
	<bean id="sm2SubjectBiz" class="com.nbcedu.function.schoolmaster2.biz.impl.SM2SubjectBizImpl">
		<property name="sm2SubjectDao" ref="sm2SubjectDao"></property>
	</bean>
	
	<bean id="sm2ModuleBiz" class="com.nbcedu.function.schoolmaster2.biz.impl.SM2ModuleBizImpl">
		<property name="sm2ModuleDao" ref="sm2ModuleDao"></property>
	</bean>
	<bean id="sm2TypeBiz" class="com.nbcedu.function.schoolmaster2.biz.impl.Sm2TypeBizImpl">
		<property name="sm2TypeDao" ref="sm2TypeDao"></property>
	</bean>
	
	<bean id="masterSubBiz" class="com.nbcedu.function.schoolmaster2.biz.impl.SM2MasterSubBizImpl">
		<property name="sm2SubjectDao" ref="sm2SubjectDao"></property>
	</bean>

	<bean id="sm2InvatitionBiz" class="com.nbcedu.function.schoolmaster2.biz.impl.SM2InvatitionBizImpl">
		<property name="sm2InvatitionDao" ref="sm2InvatitionDao"></property>
	</bean>

	<bean id="sm2ResourceBiz" class="com.nbcedu.function.schoolmaster2.biz.impl.SM2ResourceBizImpl">
		<property name="sm2ResourceDao" ref="sm2ResourceDao"></property>
	</bean>

	<bean id="sm2MasterCommentBiz" class="com.nbcedu.function.schoolmaster2.biz.impl.SM2MasterCommentBizImpl">
		<property name="sm2MasterCommentDao" ref="sm2MasterCommentDao"></property>
	</bean>
	
	<bean id="sm2MasterReplyBiz" class="com.nbcedu.function.schoolmaster2.biz.impl.SM2MasterReplyBizImpl">
		<property name="sm2MasterReplyDao" ref="sm2MasterReplyDao"></property>
	</bean>

	<bean id="sm2StepBiz" class="com.nbcedu.function.schoolmaster2.biz.impl.Sm2StepBizImpl">
		<property name="stepDao" ref="sm2StepDao"></property>
		<property name="subjectBiz" ref="sm2SubjectBiz"></property>
	</bean>
	
	<bean id="sm2ProgressBiz" class="com.nbcedu.function.schoolmaster2.biz.impl.Sm2ProgressBizImpl">
		<property name="progressDao" ref="sm2ProgressDao" />
		<property name="zanBiz" ref="sm2ZanBiz" />
		<property name="resourceBiz" ref="sm2ResourceBiz"></property>
		<property name="readsBiz" ref="sm2ReadsBiz" ></property>
		<property name="masterReplyBiz" ref="sm2MasterReplyBiz"></property>
		<property name="masterCommentBiz" ref="sm2MasterCommentBiz"></property>
		<property name="disscusBiz" ref="sm2DisscusBiz"></property>
		<property name="commentBiz" ref="sm2CommentBiz"></property>
	</bean>
	
	<bean id="sm2ZanBiz" class="com.nbcedu.function.schoolmaster2.biz.impl.SM2ZanBizImpl">
		<property name="zanDao" ref="sm2ZanDao"></property>
	</bean>
	
	<bean id="sm2ReadsBiz" class="com.nbcedu.function.schoolmaster2.biz.impl.Sm2ReadsBizImpl" >
		<property name="readsDao" ref="sm2ReadsDao" ></property>
	</bean>
	
	<bean id="sm2DisscusBiz" class="com.nbcedu.function.schoolmaster2.biz.impl.SM2DisscusBizImpl">
		<property name="disDao" ref="sm2DisscusDao"></property>
	</bean>
	<bean id="sm2TransBiz" class="com.nbcedu.function.schoolmaster2.biz.impl.SM2TransBizImpl">
		<property name="transDao" ref="sm2TransDao"></property>
	</bean>
	<bean id="sm2CommentBiz" class="com.nbcedu.function.schoolmaster2.biz.impl.SM2CommentBizImpl">
		<property name="comDao" ref="sm2CommentDao" />
	</bean>
</beans>
